metarl/__init__.py
metarl/maml.py
metarl/version.py
metarl-0.1.0.dist-info/METADATA
metarl-0.1.0.dist-info/WHEEL
metarl-0.1.0.dist-info/top_level.txt
metarl-0.1.0.dist-info/RECORD
