Metadata-Version: 2.1
Name: metarl
Version: 0.1.0
Summary: Meta Reinforcement Learning
Home-page: https://github.com/metarl/awesome-metarl
Author: Zhiqing Xiao
Author-email: xzq.xiaozhiqing@gmail.com
Classifier: Programming Language :: Python
Classifier: Intended Audience :: Science/Research
